{
  "document": {
    "document_type": "barcode",
    "templates": {
      "barcode": {
        "template_quad": [
          [
            0,
            0
          ],
          [
            1,
            0
          ],
          [
            1,
            1
          ],
          [
            0,
            1
          ]
        ]
      }
    }
  },
  "props": {
    "barcode": {
      "binary_data": "",
      "class_name": "QR_CODE",
      "dim1": "29",
      "dim2": "29",
      "finder_patterns": [
        [
          358,
          94
        ],
        [
          1500,
          200
        ],
        [
          1455,
          442
        ]
      ],
      "foreground": "",
      "module_size": [
        [
          13.975976059686246,
          14.671219767949434
        ],
        [
          14.755589422739456,
          15.667280543431398
        ]
      ],
      "private": "",
      "public": "",
      "quad": [
        [
          658.3499999999999,
          301.95000000000005
        ],
        [
          350.3499999999999,
          565.95
        ],
        [
          31.34999999999991,
          280.95000000000005
        ],
        [
          335.3499999999999,
          26.950000000000045
        ]
      ],
      "symbology": "QR_CODE",
      "value": ""
    }
  }
}