{
  "document": {
    "document_type": "barcode",
    "templates": {
      "barcode": {
        "template_quad": [
          [
            0,
            0
          ],
          [
            1,
            0
          ],
          [
            1,
            1
          ],
          [
            0,
            1
          ]
        ]
      }
    }
  },
  "props": {
    "barcode": {
      "class_name": "QR_CODE",
      "module_size": [
        [
          8.41499403704333,
          8.980296120430058
        ],
        [
          7.409263975640169,
          7.992637360591342
        ]
      ],
      "quad": [
        [
          16.69999999999999,
          12.800000000000182
        ],
        [
          305.7,
          19.800000000000182
        ],
        [
          350.7,
          268.8000000000002
        ],
        [
          70.69999999999999,
          257.8000000000002
        ]
      ],
      "symbology": "QR_CODE",
      "value": "https://smartengines.com/https://smartengines.com/https:/"
    }
  }
}