{
  "document": {
    "document_type": "barcode",
    "templates": {
      "barcode": {
        "template_quad": [
          [
            0,
            0
          ],
          [
            1,
            0
          ],
          [
            1,
            1
          ],
          [
            0,
            1
          ]
        ]
      }
    }
  },
  "props": {
    "barcode": {
      "class_name": "QR_CODE",
      "module_size": [
        [
          3.5491787669528336,
          3.6526525878122977
        ],
        [
          3.4462890625,
          3.546133141299903
        ]
      ],
      "quad": [
        [
          5.199999999999989,
          7.100000000000023
        ],
        [
          109.19999999999999,
          5.100000000000023
        ],
        [
          108.19999999999999,
          106.10000000000002
        ],
        [
          5.199999999999989,
          107.10000000000002
        ]
      ],
      "symbology": "QR_CODE",
      "value": "https://smartengines.com/https://sma"
    }
  }
}