{
  "document": {
    "document_type": "barcode",
    "templates": {
      "barcode": {
        "template_quad": [
          [
            0,
            0
          ],
          [
            1,
            0
          ],
          [
            1,
            1
          ],
          [
            0,
            1
          ]
        ]
      }
    }
  },
  "props": {
    "barcode": {
      "class_name": "QR_CODE",
      "module_size": [
        [
          8.900956210192518,
          9.025111786217403
        ],
        [
          8.88859917249056,
          9.043908907832805
        ]
      ],
      "quad": [
        [
          474.5999999999999,
          419.54999999999995
        ],
        [
          78.59999999999991,
          473.54999999999995
        ],
        [
          22.59999999999991,
          75.54999999999995
        ],
        [
          421.5999999999999,
          22.549999999999955
        ]
      ],
      "symbology": "QR_CODE",
      "value": "https://smartengines.com/https://smartengines.com/https://smartengines.com/https://smartengines.com/https://smartengines.com/https://smartengi"
    }
  }
}