{
  "document": {
    "document_type": "barcode",
    "templates": {
      "barcode": {
        "template_quad": [
          [
            0,
            0
          ],
          [
            1,
            0
          ],
          [
            1,
            1
          ],
          [
            0,
            1
          ]
        ]
      }
    }
  },
  "props": {
    "barcode": {
      "class_name": "QR_CODE",
      "module_size": [
        [
          5.858248198961485,
          5.942276501547011
        ],
        [
          5.70233154296875,
          5.854759148499596
        ]
      ],
      "quad": [
        [
          7.300000000000011,
          9.350000000000023
        ],
        [
          10.300000000000011,
          154.35000000000002
        ],
        [
          153.3,
          154.35000000000002
        ],
        [
          150.3,
          7.350000000000023
        ]
      ],
      "symbology": "QR_CODE",
      "value": "https://smartengines.com/https:"
    }
  }
}