{
  "document": {
    "document_type": "barcode",
    "templates": {
      "barcode": {
        "template_quad": [
          [
            0,
            0
          ],
          [
            1,
            0
          ],
          [
            1,
            1
          ],
          [
            0,
            1
          ]
        ]
      }
    }
  },
  "props": {
    "barcode": {
      "class_name": "QR_CODE",
      "module_size": [
        [
          8.315272643072962,
          8.727178706600334
        ],
        [
          8.158767560575706,
          8.770760897298034
        ]
      ],
      "quad": [
        [
          11.100000000000023,
          24.05000000000001
        ],
        [
          225.10000000000002,
          11.050000000000011
        ],
        [
          233.10000000000002,
          221.05
        ],
        [
          26.100000000000023,
          232.05
        ]
      ],
      "symbology": "QR_CODE",
      "value": "https://smartengines.com/h"
    }
  }
}