{
  "document": {
    "document_type": "barcode",
    "templates": {
      "barcode": {
        "template_quad": [
          [
            0,
            0
          ],
          [
            1,
            0
          ],
          [
            1,
            1
          ],
          [
            0,
            1
          ]
        ]
      }
    }
  },
  "props": {
    "barcode": {
      "class_name": "QR_CODE",
      "module_size": [
        [
          3.6638303908905936,
          3.9462381589495585
        ],
        [
          3.7645768738907432,
          4.112311660119321
        ]
      ],
      "quad": [
        [
          11.649999999999977,
          6.0499999999999545
        ],
        [
          118.64999999999998,
          15.049999999999955
        ],
        [
          116.64999999999998,
          127.04999999999995
        ],
        [
          5.649999999999977,
          120.04999999999995
        ]
      ],
      "symbology": "QR_CODE",
      "value": "https://smartengines.com/https://smarten"
    }
  }
}