{
  "document": {
    "document_type": "barcode",
    "templates": {
      "barcode": {
        "template_quad": [
          [
            0,
            0
          ],
          [
            1,
            0
          ],
          [
            1,
            1
          ],
          [
            0,
            1
          ]
        ]
      }
    }
  },
  "props": {
    "barcode": {
      "class_name": "QR_CODE",
      "module_size": [
        [
          3.438861247946014,
          3.5069794972034973
        ],
        [
          3.451483919104834,
          3.538486663337344
        ]
      ],
      "quad": [
        [
          27.75,
          10.150000000000091
        ],
        [
          225.75,
          16.15000000000009
        ],
        [
          206.75,
          213.1500000000001
        ],
        [
          10.75,
          208.1500000000001
        ]
      ],
      "symbology": "QR_CODE",
      "value": "https://smartengines.com/https://smartengines.com/https://smartengines.com/https://smartengines.com/https://smartengines.com/https://smartengines.com/https://smartengines.com/https://smartengines.com/https://smartengines.com/https://smartengines.com/https://smartengines."
    }
  }
}