{
  "document": {
    "document_type": "barcode",
    "templates": {
      "barcode": {
        "template_quad": [
          [
            0,
            0
          ],
          [
            1,
            0
          ],
          [
            1,
            1
          ],
          [
            0,
            1
          ]
        ]
      }
    }
  },
  "props": {
    "barcode": {
      "class_name": "QR_CODE",
      "module_size": [
        [
          4.439723875602163,
          4.952924475010313
        ],
        [
          3.9517903267026164,
          4.6251512358560225
        ]
      ],
      "quad": [
        [
          8.149999999999977,
          13.200000000000045
        ],
        [
          167.14999999999998,
          7.2000000000000455
        ],
        [
          171.14999999999998,
          148.20000000000005
        ],
        [
          23.149999999999977,
          151.20000000000005
        ]
      ],
      "symbology": "QR_CODE",
      "value": "https://smartengines.com/https://smartengines.com/https://sma"
    }
  }
}