{
  "document": {
    "document_type": "barcode",
    "templates": {
      "barcode": {
        "template_quad": [
          [
            0,
            0
          ],
          [
            1,
            0
          ],
          [
            1,
            1
          ],
          [
            0,
            1
          ]
        ]
      }
    }
  },
  "props": {
    "barcode": {
      "class_name": "QR_CODE",
      "module_size": [
        [
          16.397180181465565,
          16.950306082313748
        ],
        [
          15.855799891680824,
          16.740221364700876
        ]
      ],
      "quad": [
        [
          58.44999999999999,
          26.799999999999955
        ],
        [
          597.45,
          30.799999999999955
        ],
        [
          581.45,
          562.8
        ],
        [
          28.44999999999999,
          560.8
        ]
      ],
      "symbology": "QR_CODE",
      "value": "https://smartengines.com/https://smartengines.com/https://smartengines.com/htt"
    }
  }
}