{
  "document": {
    "document_type": "barcode",
    "templates": {
      "barcode": {
        "template_quad": [
          [
            0,
            0
          ],
          [
            1,
            0
          ],
          [
            1,
            1
          ],
          [
            0,
            1
          ]
        ]
      }
    }
  },
  "props": {
    "barcode": {
      "class_name": "QR_CODE",
      "module_size": [
        [
          5.000841495084428,
          5.6249588084865065
        ],
        [
          4.110798944862704,
          4.953364846503467
        ]
      ],
      "quad": [
        [
          8.199999999999989,
          7.5499999999999545
        ],
        [
          167.2,
          6.5499999999999545
        ],
        [
          172.2,
          134.54999999999995
        ],
        [
          26.19999999999999,
          137.54999999999995
        ]
      ],
      "symbology": "QR_CODE",
      "value": "https://smartengines.com/https://smartengine"
    }
  }
}