{
  "document": {
    "document_type": "barcode",
    "templates": {
      "barcode": {
        "template_quad": [
          [
            0,
            0
          ],
          [
            1,
            0
          ],
          [
            1,
            1
          ],
          [
            0,
            1
          ]
        ]
      }
    }
  },
  "props": {
    "barcode": {
      "class_name": "QR_CODE",
      "module_size": [
        [
          22.134371486484735,
          22.809911928927185
        ],
        [
          21.809929072150716,
          22.231897175849056
        ]
      ],
      "quad": [
        [
          33.39999999999998,
          677.5999999999999
        ],
        [
          73.39999999999998,
          33.59999999999991
        ],
        [
          701.4,
          59.59999999999991
        ],
        [
          670.4,
          705.5999999999999
        ]
      ],
      "symbology": "QR_CODE",
      "value": "https://smartengines.com/https://smartengines.com/h"
    }
  }
}