{
  "document": {
    "document_type": "barcode",
    "templates": {
      "barcode": {
        "template_quad": [
          [
            0,
            0
          ],
          [
            1,
            0
          ],
          [
            1,
            1
          ],
          [
            0,
            1
          ]
        ]
      }
    }
  },
  "props": {
    "barcode": {
      "class_name": "QR_CODE",
      "module_size": [
        [
          21.57527810921173,
          23.410693661030237
        ],
        [
          21.355854953032,
          23.55619985934918
        ]
      ],
      "quad": [
        [
          50.44999999999982,
          681.9000000000001
        ],
        [
          33.44999999999982,
          48.90000000000009
        ],
        [
          670.4499999999998,
          32.90000000000009
        ],
        [
          702.4499999999998,
          690.9000000000001
        ]
      ],
      "symbology": "QR_CODE",
      "value": "https://smartengines.com/https://smartengines.com/htt"
    }
  }
}