{
  "document": {
    "document_type": "barcode",
    "templates": {
      "barcode": {
        "template_quad": [
          [
            0,
            0
          ],
          [
            1,
            0
          ],
          [
            1,
            1
          ],
          [
            0,
            1
          ]
        ]
      }
    }
  },
  "props": {
    "barcode": {
      "class_name": "QR_CODE",
      "module_size": [
        [
          9.637851462105184,
          10.596484342377074
        ],
        [
          9.185170970191482,
          10.699931945790471
        ]
      ],
      "quad": [
        [
          52.80000000000001,
          15.450000000000045
        ],
        [
          331.8,
          38.450000000000045
        ],
        [
          315.8,
          324.45000000000005
        ],
        [
          15.800000000000011,
          296.45000000000005
        ]
      ],
      "symbology": "QR_CODE",
      "value": "https://smartengines.com/https://s"
    }
  }
}